LICENSE_code.md
LICENSE_doc.md
MANIFEST.in
README.md
pyproject.toml
requirements.txt
setup.py
doc/img/algorithm.png
doc/img/logo.png
doc/img/logo_small.png
tests/requirements_test.txt
tests/test.py
torch_discounted_cumsum/__init__.py
torch_discounted_cumsum/discounted_cumsum.py
torch_discounted_cumsum/discounted_cumsum_cpu.cpp
torch_discounted_cumsum/discounted_cumsum_cuda.cpp
torch_discounted_cumsum/discounted_cumsum_cuda_kernel.cu
torch_discounted_cumsum/version.py
torch_discounted_cumsum.egg-info/PKG-INFO
torch_discounted_cumsum.egg-info/SOURCES.txt
torch_discounted_cumsum.egg-info/dependency_links.txt
torch_discounted_cumsum.egg-info/requires.txt
torch_discounted_cumsum.egg-info/top_level.txt