Metadata-Version: 2.1
Name: torch-discounted-cumsum
Version: 1.1.0
Summary: Fast discounted cumulative sums in PyTorch
Home-page: https://www.github.com/toshas/torch-discounted-cumsum
Author: Anton Obukhov
License: BSD
Keywords: pytorch,discounted,cumsum,cumulative,sum,scan,differentiable,reinforcement,learning,rewards,time,series
Platform: UNKNOWN
Requires-Python: >=3.6
License-File: LICENSE_code.md
License-File: LICENSE_doc.md
